vgis_spider/__init__.py
vgis_spider/downloadTilesTools - 副本.py
vgis_spider/downloadTilesTools.py
vgis_spider/htmlParse.py
vgis_spider/specialValue.py
vgis_spider/spiderTest.py
vgis_spider/weiboCrawler.py
vgis_spider/weiboSettings.py
vgis_spider/weixinCrawler.py
vgis_spider-1.1.9.dist-info/METADATA
vgis_spider-1.1.9.dist-info/WHEEL
vgis_spider-1.1.9.dist-info/top_level.txt
vgis_spider-1.1.9.dist-info/RECORD
